used_cars/__init__.py
used_cars/inference.py
used_cars/preprocess.py
used_cars/train.py
used_cars_gst-0.0.4.dist-info/LICENSE.txt
used_cars_gst-0.0.4.dist-info/METADATA
used_cars_gst-0.0.4.dist-info/WHEEL
used_cars_gst-0.0.4.dist-info/top_level.txt
used_cars_gst-0.0.4.dist-info/RECORD
