Metadata-Version: 2.1
Name: used-cars-gst
Version: 0.0.4
Summary: Data Science in Production
Home-page: https://github.com/GuitooStephan/dsp-used-cars-prediction
Author: Stephane Tanoh
Author-email: guystephane00@gmail.com
Project-URL: Bug Tracker, https://github.com/GuitooStephan/dsp-used-cars-prediction/issues
Classifier: Programming Language :: Python :: 3
Classifier: License :: OSI Approved :: MIT License
Classifier: Operating System :: OS Independent
Requires-Python: >=3.6
License-File: LICENSE.txt
Requires-Dist: pandas (==1.4.1)
Requires-Dist: scikit-learn (==1.0.2)
Requires-Dist: scipy (==1.8.0)
Requires-Dist: joblib (==1.1.0)
